{
  "project_info": {
    "project_number": "239741100514",
    "project_id": "smsgoforward",
    "storage_bucket": "smsgoforward.appspot.com"
  },
  "client": [
    {
      "client_info": {
        "mobilesdk_app_id": "1:239741100514:android:cb2c838ebd8931932799bb",
        "android_client_info": {
          "package_name": "com.radwil.sms"
        }
      },
      "oauth_client": [
        {
          "client_id": "239741100514-k8kkeb8q9bq9j55g6aan0si790ffhlil.apps.googleusercontent.com",
          "client_type": 3
        }
      ],
      "api_key": [
        {
          "current_key": "AIzaSyDAATXNWtvHATY1wbd9mXDPwCuT-t2Lu5s"
        }
      ],
      "services": {
        "appinvite_service": {
          "other_platform_oauth_client": [
            {
              "client_id": "239741100514-k8kkeb8q9bq9j55g6aan0si790ffhlil.apps.googleusercontent.com",
              "client_type": 3
            }
          ]
        }
      }
    }
  ],
  "configuration_version": "1"
}